pysqltools/.DS_Store
pysqltools/__init__.py
pysqltools/src/__init__.py
pysqltools/src/log/__init__.py
pysqltools/src/log/log.py
pysqltools/src/sql/__init__.py
pysqltools/src/sql/constants.py
pysqltools/src/sql/delete.py
pysqltools/src/sql/exceptions.py
pysqltools/src/sql/insert.py
pysqltools/src/sql/query.py
pysqltools/src/sql/table.py
pysqltools-1.1.0.dist-info/METADATA
pysqltools-1.1.0.dist-info/WHEEL
pysqltools-1.1.0.dist-info/RECORD
