Metadata-Version: 2.1
Name: pysqltools
Version: 1.1.0
Summary: PySQLTools
License: None
Author: Pablo Minué
Requires-Python: >=3.10,<4.0
Classifier: License :: Other/Proprietary License
Classifier: Programming Language :: Python :: 3
Classifier: Programming Language :: Python :: 3.10
Classifier: Programming Language :: Python :: 3.11
Classifier: Programming Language :: Python :: 3.12
Classifier: Programming Language :: Python :: 3.13
Requires-Dist: multimethod (>=1.11.2,<2.0.0)
Requires-Dist: pandas (>=2.2.2,<3.0.0)
Requires-Dist: pillow (>=10.3.0,<11.0.0)
Requires-Dist: pylint (>=3.3.4,<4.0.0)
Requires-Dist: rich (>=13.9.4,<14.0.0)
Requires-Dist: sqlparse (>=0.5.0,<0.6.0)
